abe/main.py
abe_bft-1.0.0.dist-info/METADATA
abe_bft-1.0.0.dist-info/WHEEL
abe_bft-1.0.0.dist-info/entry_points.txt
abe_bft-1.0.0.dist-info/top_level.txt
abe_bft-1.0.0.dist-info/RECORD
