Metadata-Version: 2.4
Name: abe-bft
Version: 1.0.0
Summary: Absolute Byzantine Engine - A BFT-based AI trading analysis tool.
Classifier: Programming Language :: Python :: 3
Classifier: License :: OSI Approved :: MIT License
Classifier: Operating System :: OS Independent
Requires-Python: >=3.8
Requires-Dist: anthropic
Requires-Dist: groq
Requires-Dist: yfinance
Requires-Dist: ccxt
Requires-Dist: python-dotenv
Requires-Dist: colorama
Requires-Dist: requests
Requires-Dist: plyer
